[
  {
    "id": "shortblade_quick_jab",
    "name": "Quick Jab",
    "description": "A rapid dagger jab that finds gaps in enemy guard.",
    "skillId": "skill_melee_shortBlade",
    "unlockSkillLevelMin": 0,
    "mpCostBase": 3,
    "cooldownMsBase": 2000,
    "damageBase": 6,
    "maxTargets": 1,
    "allowedWeaponClasses": ["melee"],
    "requiredWeaponSubTypes": ["shortBlade"],
    "requiresWeaponEquipped": true,
    "castUsesWeaponDamageModel": true,
    "attributeDamageScale": {"STR": 0.9, "VIT": 0.1}
  },
  {
    "id": "shortblade_backstab",
    "name": "Backstab",
    "description": "A swift dagger thrust that strikes from the shadows for heavy damage using your weapon's damage.",
    "skillId": "skill_melee_shortBlade",
    "unlockSkillLevelMin": 4,
    "mpCostBase": 6,
    "cooldownMsBase": 2000,
    "maxTargets": 1,
    "allowedWeaponClasses": ["melee"],
    "requiredWeaponSubTypes": ["shortBlade"],
    "requiresWeaponEquipped": true,
    "castUsesWeaponDamageModel": true,
    "attributeDamageScale": {"STR": 0.9, "VIT": 0.1}
  },
  {
    "id": "shortblade_flurry",
    "name": "Blade Flurry",
    "description": "A flurry of quick dagger slashes that strikes multiple nearby foes.",
    "skillId": "skill_melee_shortBlade",
    "unlockSkillLevelMin": 6,
    "mpCostBase": 8,
    "cooldownMsBase": 3000,
    "damageBase": 14,
    "maxTargets": 3,
    "allowedWeaponClasses": ["melee"],
    "requiredWeaponSubTypes": ["shortBlade"],
    "requiresWeaponEquipped": true,
    "castUsesWeaponDamageModel": true,
    "abilityType": "cone",
    "attributeDamageScale": {"STR": 0.9, "VIT": 0.1}
  }
]
